fw/__init__.py
fw/apps.py
fw/managers.py
fw/models.py
fw/querysets.py
fw/tests.py
fw/validators.py
fw/admin/__init__.py
fw/admin/actions.py
fw/admin/apps.py
fw/admin/options.py
fw/import_export/__init__.py
fw/import_export/defs.py
fw/import_export/resources.py
fw/import_export/widgets.py
fw/rest/__init__.py
fw/rest/pagination.py
fw/rest/permissions.py
fw/rest/serializers.py
fw/rest/views.py
fwbasemodel-1.0.1.dist-info/LICENCE
fwbasemodel-1.0.1.dist-info/METADATA
fwbasemodel-1.0.1.dist-info/WHEEL
fwbasemodel-1.0.1.dist-info/top_level.txt
fwbasemodel-1.0.1.dist-info/RECORD
